netbox_routing/__init__.py
netbox_routing/urls.py
netbox_routing/api/__init__.py
netbox_routing/api/serializers.py
netbox_routing/api/urls.py
netbox_routing/api/_serializers/__init__.py
netbox_routing/api/_serializers/bgp.py
netbox_routing/api/_serializers/eigrp.py
netbox_routing/api/_serializers/objects.py
netbox_routing/api/_serializers/ospf.py
netbox_routing/api/_serializers/static.py
netbox_routing/api/field_serializers/__init__.py
netbox_routing/api/field_serializers/ip.py
netbox_routing/api/views/__init__.py
netbox_routing/api/views/bgp.py
netbox_routing/api/views/eigrp.py
netbox_routing/api/views/objects.py
netbox_routing/api/views/ospf.py
netbox_routing/api/views/static.py
netbox_routing/choices/__init__.py
netbox_routing/choices/base.py
netbox_routing/choices/bgp.py
netbox_routing/choices/eigrp.py
netbox_routing/choices/objects.py
netbox_routing/choices/ospf.py
netbox_routing/constants/__init__.py
netbox_routing/constants/bgp.py
netbox_routing/constants/eigrp.py
netbox_routing/fields/__init__.py
netbox_routing/fields/ip.py
netbox_routing/filtersets/__init__.py
netbox_routing/filtersets/bgp.py
netbox_routing/filtersets/eigrp.py
netbox_routing/filtersets/objects.py
netbox_routing/filtersets/ospf.py
netbox_routing/filtersets/static.py
netbox_routing/forms/__init__.py
netbox_routing/forms/bgp.py
netbox_routing/forms/eigrp.py
netbox_routing/forms/fields.py
netbox_routing/forms/objects.py
netbox_routing/forms/ospf.py
netbox_routing/forms/static.py
netbox_routing/forms/bulk_edit/__init__.py
netbox_routing/forms/bulk_edit/eigrp.py
netbox_routing/forms/bulk_edit/objects.py
netbox_routing/forms/bulk_edit/ospf.py
netbox_routing/forms/bulk_edit/static.py
netbox_routing/forms/bulk_import/__init__.py
netbox_routing/forms/bulk_import/eigrp.py
netbox_routing/forms/bulk_import/ospf.py
netbox_routing/forms/bulk_import/static.py
netbox_routing/forms/filtersets/__init__.py
netbox_routing/forms/filtersets/bgp.py
netbox_routing/forms/filtersets/eigrp.py
netbox_routing-0.3.2.dist-info/licenses/LICENSE
netbox_routing-0.3.2.dist-info/METADATA
netbox_routing-0.3.2.dist-info/WHEEL
netbox_routing-0.3.2.dist-info/top_level.txt
netbox_routing-0.3.2.dist-info/RECORD
