Metadata-Version: 2.4
Name: netbox-routing
Version: 0.3.2
Summary: A NetBox Routing Plugin
Author-email: Daniel Sheppard <dans@dansheps.com>
Maintainer-email: Daniel Sheppard <dans@dansheps.com>
License:                                  Apache License
Project-URL: Documentation, https://github.com/dansheps/netbox-routing/blob/main/README.md
Project-URL: Source, https://github.com/dansheps/netbox-routing
Project-URL: Tracker, https://github.com/dansheps/netbox-routing/issues
Keywords: netbox-plugin
Classifier: Programming Language :: Python :: 3
Requires-Python: >=3.12
License-File: LICENSE
Requires-Dist: django-polymorphic
Dynamic: license-file
